geolocation/__init__.py
geolocation/geolocation.py
latlongtimezone_api-0.1.91.dist-info/LICENSE
latlongtimezone_api-0.1.91.dist-info/METADATA
latlongtimezone_api-0.1.91.dist-info/WHEEL
latlongtimezone_api-0.1.91.dist-info/top_level.txt
latlongtimezone_api-0.1.91.dist-info/RECORD
