Metadata-Version: 2.1
Name: latlongtimezone_api
Version: 0.1.91
Summary: Get timezone, locale, and location based on the IP address to use in your requests
Home-page: https://github.com/pim97/requests-lat-long-timezone-locale-ip-api
Author: dormic97
Author-email: crozz-boy@hotmail.com
License: MIT
Keywords: ip,ip-api,ip-geolocation,ip-location,ip-address,ip-locator,ip-tracker,ip-geocoding,ip-api-geolocation,ip-api-location,ip-api-address,ip-api-locator,ip-api-tracker,ip-api-geocoding
Classifier: Development Status :: 5 - Production/Stable
Classifier: Intended Audience :: Developers
Classifier: Topic :: Software Development :: Build Tools
Classifier: License :: OSI Approved :: MIT License
Classifier: Programming Language :: Python :: 3
Classifier: Programming Language :: Python :: 3.4
Classifier: Programming Language :: Python :: 3.5
Classifier: Programming Language :: Python :: 3.6
License-File: LICENSE
Requires-Dist: requests
Requires-Dist: redis
Requires-Dist: python-dotenv
